do_to_ssh_config/__init__.py
do_to_ssh_config/do_to_ssh_config.py
do_to_ssh_config-0.0.4.dist-info/METADATA
do_to_ssh_config-0.0.4.dist-info/RECORD
do_to_ssh_config-0.0.4.dist-info/WHEEL
do_to_ssh_config-0.0.4.dist-info/top_level.txt
