Metadata-Version: 2.1
Name: do-to-ssh-config
Version: 0.0.4
Summary: Combine DO droplets with your ssh configuration
Home-page: https://github.com/hytromo/digital-ocean-to-ssh-config
Author: Alexandros Solanos
Author-email: solanosalex@gmail.com
License: UNKNOWN
Platform: UNKNOWN
Classifier: Programming Language :: Python :: 3
Classifier: License :: OSI Approved :: MIT License
Classifier: Operating System :: OS Independent
Requires-Dist: python-digitalocean
